doc/accounting.py
pomagma/__init__.py
pomagma/__main__.py
pomagma/make.py
pomagma/workers.py
pomagma/workers_test.py
pomagma/analyst/__init__.py
pomagma/analyst/analyst_messages_pb2.py
pomagma/analyst/client.py
pomagma/analyst/client_test.py
pomagma/analyst/compiler.py
pomagma/analyst/compiler_test.py
pomagma/analyst/server.py
pomagma/analyst/startup.py
pomagma/analyst/synthesize.py
pomagma/analyst/synthesize_test.py
pomagma/analyst/testdata/make.py
pomagma/atlas/__init__.py
pomagma/atlas/__main__.py
pomagma/atlas/atlas_test.py
pomagma/atlas/bootstrap.py
pomagma/atlas/structure_pb2.py
pomagma/cartographer/__init__.py
pomagma/cartographer/cartographer_messages_pb2.py
pomagma/cartographer/client.py
pomagma/cartographer/server.py
pomagma/cartographer/server_test.py
pomagma/compiler/__init__.py
pomagma/compiler/__main__.py
pomagma/compiler/compiler.py
pomagma/compiler/compiler_test.py
pomagma/compiler/completion.py
pomagma/compiler/expressions.py
pomagma/compiler/expressions_test.py
pomagma/compiler/extensional.py
pomagma/compiler/extensional_test.py
pomagma/compiler/frontend.py
pomagma/compiler/frontend_test.py
pomagma/compiler/parser.py
pomagma/compiler/parser_test.py
pomagma/compiler/plans.py
pomagma/compiler/presentation.py
pomagma/compiler/sequencer.py
pomagma/compiler/sequencer_test.py
pomagma/compiler/sequents.py
pomagma/compiler/sequents_test.py
pomagma/compiler/signature.py
pomagma/compiler/signature_test.py
pomagma/compiler/simplify.py
pomagma/compiler/simplify_test.py
pomagma/compiler/sugar.py
pomagma/compiler/sugar_test.py
pomagma/compiler/syntax_pb2.py
pomagma/compiler/util.py
pomagma/compiler/util_test.py
pomagma/corpus/__init__.py
pomagma/corpus/__main__.py
pomagma/corpus/corpus.py
pomagma/examples/__init__.py
pomagma/examples/definable_types.py
pomagma/examples/definable_types_test.py
pomagma/examples/solve.py
pomagma/examples/solve_test.py
pomagma/examples/sudoku.py
pomagma/examples/sudoku_test.py
pomagma/examples/synthesize.py
pomagma-0.3.1.dist-info/licenses/LICENSE
pomagma-0.3.1.dist-info/METADATA
pomagma-0.3.1.dist-info/WHEEL
pomagma-0.3.1.dist-info/entry_points.txt
pomagma-0.3.1.dist-info/top_level.txt
pomagma-0.3.1.dist-info/RECORD
