Metadata-Version: 2.4
Name: pomagma
Version: 0.3.1
Summary: An inference engine for extensional lambda-calculus
Author-email: Fritz Obermeyer <fritz.obermeyer@gmail.com>
Maintainer-email: Fritz Obermeyer <fritz.obermeyer@gmail.com>
License-Expression: Apache-2.0
Project-URL: Homepage, https://github.com/fritzo/pomagma
Project-URL: Repository, https://github.com/fritzo/pomagma
Classifier: Development Status :: 4 - Beta
Classifier: Intended Audience :: Developers
Classifier: Programming Language :: Python :: 3
Classifier: Programming Language :: Python :: 3.11
Classifier: Programming Language :: Python :: 3.12
Classifier: Programming Language :: Python :: 3.13
Requires-Python: >=3.11
License-File: LICENSE
Requires-Dist: boto3
Requires-Dist: hypothesis
Requires-Dist: immutables
Requires-Dist: isort
Requires-Dist: mypy
Requires-Dist: nbval
Requires-Dist: notebook
Requires-Dist: numpy
Requires-Dist: parsable
Requires-Dist: protobuf<6,>=5
Requires-Dist: psutil
Requires-Dist: pytest
Requires-Dist: pytest-timeout
Requires-Dist: pytest-xdist
Requires-Dist: pyzmq
Requires-Dist: ruff
Requires-Dist: torch
Requires-Dist: tqdm
Dynamic: license-file
